easiersocket/__init__.py
easiersocket/core.py
Easiersocket-0.1.1.dist-info/METADATA
Easiersocket-0.1.1.dist-info/WHEEL
Easiersocket-0.1.1.dist-info/top_level.txt
Easiersocket-0.1.1.dist-info/RECORD
