Metadata-Version: 2.1
Name: Easiersocket
Version: 0.1.1
Summary: easysocket library for easier socket processing
Home-page: https://github.com/teddylee777/teddynote
Author: gamewithmouse
Author-email: gamewithmouse <author@example.com>
Project-URL: Homepage, https://github.com/gamewithmouse/easysocket
Project-URL: Issues, https://github.com/gamewithmouse/easysocket/issues
Classifier: Programming Language :: Python :: 3
Classifier: License :: OSI Approved :: MIT License
Classifier: Operating System :: OS Independent
Requires-Python: >=3.6
